entity/__init__.py
entity/apps.py
entity/config.py
entity/constants.py
entity/exceptions.py
entity/models.py
entity/signal_handlers.py
entity/sync.py
entity/urls.py
entity/version.py
entity/management/__init__.py
entity/management/commands/__init__.py
entity/management/commands/sync_entities.py
entity/migrations/0001_0010_squashed.py
entity/migrations/0001_initial.py
entity/migrations/0002_entitygroup_logic_string.py
entity/migrations/0002_entitykind_is_active.py
entity/migrations/0003_auto_20150813_2234.py
entity/migrations/0004_auto_20150915_1747.py
entity/migrations/0005_remove_entitygroup_entities.py
entity/migrations/0006_entity_relationship_unique.py
entity/migrations/0007_allentityproxy.py
entity/migrations/0008_auto_20180329_1934.py
entity/migrations/0009_auto_20180402_2145.py
entity/migrations/0010_auto_20181213_1817.py
entity/migrations/__init__.py
entity/tests/__init__.py
entity/tests/model_tests.py
entity/tests/models.py
entity/tests/registry_tests.py
entity/tests/sync_tests.py
entity/tests/utils.py
entity/tests/migrations/0001_initial.py
entity/tests/migrations/__init__.py
django_entity-6.2.3.dist-info/LICENSE
django_entity-6.2.3.dist-info/METADATA
django_entity-6.2.3.dist-info/WHEEL
django_entity-6.2.3.dist-info/top_level.txt
django_entity-6.2.3.dist-info/RECORD
