Metadata-Version: 2.1
Name: django-entity
Version: 6.2.3
Summary: Entity relationship management for Django
Home-page: http://github.com/ambitioninc/django-entity/
Author: Wes Kendall
Author-email: wesleykendall@gmail.com
Classifier: Programming Language :: Python
Classifier: Programming Language :: Python :: 3.7
Classifier: Programming Language :: Python :: 3.8
Classifier: Programming Language :: Python :: 3.9
Classifier: Intended Audience :: Developers
Classifier: License :: OSI Approved :: MIT License
Classifier: Operating System :: OS Independent
Classifier: Framework :: Django
Classifier: Framework :: Django :: 3.2
Classifier: Framework :: Django :: 4.0
Classifier: Framework :: Django :: 4.1
Classifier: Framework :: Django :: 4.2
License-File: LICENSE
Requires-Dist: Django >=3.2
Requires-Dist: django-activatable-model >=3.1.0
Requires-Dist: django-manager-utils >=3.1.0
Requires-Dist: python3-utils >=0.3
Requires-Dist: wrapt >=1.10.5
Provides-Extra: dev
Requires-Dist: coverage ; extra == 'dev'
Requires-Dist: django-nose ; extra == 'dev'
Requires-Dist: django-dynamic-fixture ; extra == 'dev'
Requires-Dist: psycopg2 ; extra == 'dev'
Requires-Dist: flake8 ; extra == 'dev'
